connex/__init__.py
connex/_network.py
connex/_plasticity.py
connex/_utils.py
connex/nn/__init__.py
connex/nn/_dense_mlp.py
connex/nn/_mlp.py
connex/nn/_utils.py
connex-0.3.3.dist-info/METADATA
connex-0.3.3.dist-info/WHEEL
connex-0.3.3.dist-info/licenses/LICENSE
connex-0.3.3.dist-info/RECORD
