Metadata-Version: 2.1
Name: connex
Version: 0.3.3
Summary: Fine-grained, dynamic control of neural network topology in JAX.
Project-URL: repository, https://github.com/leonard-gleyzer/connex
Author-email: Leonard Gleyzer <lenny@lenn.ai>
License:                                  Apache License
License-File: LICENSE
Keywords: deep-learning,jax,neural-networks
Classifier: Development Status :: 3 - Alpha
Classifier: Intended Audience :: Developers
Classifier: Intended Audience :: Financial and Insurance Industry
Classifier: Intended Audience :: Information Technology
Classifier: Intended Audience :: Science/Research
Classifier: License :: OSI Approved :: Apache Software License
Classifier: Natural Language :: English
Classifier: Programming Language :: Python :: 3
Classifier: Topic :: Scientific/Engineering :: Artificial Intelligence
Classifier: Topic :: Scientific/Engineering :: Information Analysis
Classifier: Topic :: Scientific/Engineering :: Mathematics
Requires-Python: ~=3.9
Requires-Dist: equinox>=0.10.5
Requires-Dist: jax>=0.4.4
Requires-Dist: networkx>=0.3.0
